myshowsapi/__init__.py
myshowsapi/api.py
myshowsapi/exceptions.py
myshowsapi/session.py
myshowsapi-0.1.5.dist-info/DESCRIPTION.rst
myshowsapi-0.1.5.dist-info/METADATA
myshowsapi-0.1.5.dist-info/RECORD
myshowsapi-0.1.5.dist-info/WHEEL
myshowsapi-0.1.5.dist-info/metadata.json
myshowsapi-0.1.5.dist-info/top_level.txt
