Metadata-Version: 2.0
Name: myshowsapi
Version: 0.1.5
Summary: API wrapper for http://api.myshows.me/
Home-page: http://github.com/kreedz/myshowsapi
Author: Artur Tukaev
Author-email: UNKNOWN
License: MIT
Download-URL: https://github.com/kreedz/myshowsapi/archive/0.1.5.tar.gz
Keywords: myshows.me myshows api
Platform: UNKNOWN
Classifier: Intended Audience :: Developers
Classifier: License :: OSI Approved :: MIT License
Classifier: Programming Language :: Python :: 3.4
Requires-Dist: requests
